chemivec-0.1.1.dist-info/entry_points.txt
chemivec-0.1.1.dist-info/WHEEL
chemivec-0.1.1.dist-info/RECORD
chemivec-0.1.1.dist-info/METADATA
chemivec/search.py
chemivec/_chemivec.so
chemivec/__init__.py
chemivec/options.py
chemivec.libs/libgomp-a34b3233.so.1.0.0
