Metadata-Version: 2.1
Name: chemivec
Version: 0.1.1
Summary: Vectorized cheminformatics library leveraging EPAM Indigo Toolkit
Project-URL: Homepage, https://github.com/alkorolyov/chemivec
Requires-Python: >=3.8
Requires-Dist: numpy>=1.7
Requires-Dist: pandas
